dpoc
