Metadata-Version: 1.0
Name: dpoc
Version: 0.1.3
Summary: Dumb Python OpenTSDB Client
Home-page: http://github.com/lexh/dpoc
Author: Lex Herbert
Author-email: lex.herbert@gmail.com
License: MIT
Platform: UNKNOWN
